lancedb_haystack/__about__.py
lancedb_haystack/__init__.py
lancedb_haystack/document_store.py
lancedb_haystack/embedding_retriever.py
lancedb_haystack/filters.py
lancedb_haystack/fts_retriever.py
lancedb_haystack/conversion/__init__.py
lancedb_haystack/conversion/lancedb_to_python.py
lancedb_haystack/conversion/python_to_lancedb.py
lancedb_haystack/schema/__init__.py
lancedb_haystack/schema/serialization.py
lancedb_haystack-0.1.1.dist-info/METADATA
lancedb_haystack-0.1.1.dist-info/WHEEL
lancedb_haystack-0.1.1.dist-info/licenses/LICENSE
lancedb_haystack-0.1.1.dist-info/RECORD
