Metadata-Version: 2.3
Name: lancedb-haystack
Version: 0.1.1
Summary: LanceDB backed datastore and retrievers for Haystack 2.X
Project-URL: Documentation, https://github.com/alanmeeson/lancedb-haystack#readme
Project-URL: Issues, https://github.com/alanmeeson/lancedb-haystack/issues
Project-URL: Source, https://github.com/alanmeeson/lancedb-haystack
Author-email: Alan Meeson <am@carefullycalculated.co.uk>
License-Expression: Apache-2.0
License-File: LICENSE
Classifier: Development Status :: 4 - Beta
Classifier: Programming Language :: Python
Classifier: Programming Language :: Python :: 3.7
Classifier: Programming Language :: Python :: 3.8
Classifier: Programming Language :: Python :: 3.9
Classifier: Programming Language :: Python :: 3.10
Classifier: Programming Language :: Python :: 3.11
Classifier: Programming Language :: Python :: Implementation :: CPython
Classifier: Programming Language :: Python :: Implementation :: PyPy
Requires-Python: >=3.7
Requires-Dist: duckdb
Requires-Dist: haystack-ai
Requires-Dist: lancedb
Requires-Dist: pandas
Requires-Dist: pyarrow
Requires-Dist: tantivy
Requires-Dist: typing-extensions
